{"id":"68657060619443656", "giveSurvey":false, "type":"session", "title":"Big Data for the Enterprise - High Availability and Disaster Recovery with MarkLogic", "plenary":false, "selectable":true, "startTime__date":"2012-05-01T15:15:00-04:00", "endTime__date":"2012-05-01T16:15:00-04:00", "track":"Technical", "location":"Hemisphere A", "abstract":"What happens to your business when a machine fails or your data center suffers a catastrophic event? Wayne Feick, Principal Engineer working on MarkLogic Server, will describe how to keep your application running in the face of individual host failures or even the loss of your entire data center. Technologies discussed will include forest-level failover, replication, distributed transactions, backups, and point-in-time recovery.", "speakers":[{"affiliation":"MarkLogic", "bio":"", "email":"", "name":"Wayne Feick", "title":"Principal Engineer"}], "surveys":[{"comments":"", "speakerRating":4, "contentRating":5},{"comments":"", "speakerRating":4, "contentRating":4},{"comments":"", "speakerRating":5, "contentRating":5},{"comments":"Concise presentation of very useful information.", "speakerRating":5, "contentRating":5},{"comments":"Need some examples.  There was good explanation but some examples and some step by steps would be great", "speakerRating":4, "contentRating":5},{"comments":"Good talk. Need more details on failover in clusters and replication and what to plan for.", "speakerRating":4, "contentRating":3},{"comments":"", "speakerRating":5, "contentRating":4},{"comments":"", "speakerRating":4, "contentRating":5}]}